<?xml version="1.0" encoding="UTF-8" standalone="yes"?>
<idPkg:Spread xmlns:idPkg="http://ns.adobe.com/AdobeInDesign/idml/1.0/packaging" DOMVersion="14.0">
	<Spread Self="ue1" FlattenerOverride="Default" ShowMasterItems="true" PageCount="2" BindingLocation="1" AllowPageShuffle="true" ItemTransform="1 0 0 1 0 3960" PageTransitionType="None" PageTransitionDirection="NotApplicable" PageTransitionDuration="Medium">
		<FlattenerPreference LineArtAndTextResolution="300" GradientAndMeshResolution="150" ClipComplexRegions="false" ConvertAllStrokesToOutlines="false" ConvertAllTextToOutlines="false">
			<Properties>
				<RasterVectorBalance type="double">50</RasterVectorBalance>
			</Properties>
		</FlattenerPreference>
		<Page Self="u168" Name="10" AppliedTrapPreset="TrapPreset/$ID/kDefaultTrapStyleName" GeometricBounds="0 0 612 792" ItemTransform="1 0 0 1 -792 -306" AppliedAlternateLayout="ucd" LayoutRule="UseMaster" SnapshotBlendingMode="IgnoreLayoutSnapshots" OptionalPage="false" AppliedMaster="uce" OverrideList="" MasterPageTransform="1 0 0 1 90 -90" TabOrder="" GridStartingPoint="TopOutside" UseMasterGrid="false">
			<Properties>
				<PageColor type="enumeration">UseMasterColor</PageColor>
				<Descriptor type="list">
					<ListItem type="string"></ListItem>
					<ListItem type="enumeration">Arabic</ListItem>
					<ListItem type="boolean">true</ListItem>
					<ListItem type="boolean">false</ListItem>
					<ListItem type="long">10</ListItem>
					<ListItem type="string"></ListItem>
				</Descriptor>
			</Properties>
			<MarginPreference ColumnCount="1" ColumnGutter="12" Top="36" Bottom="36" Left="36" Right="36" ColumnDirection="Horizontal" ColumnsPositions="0 720" />
			<GridDataInformation FontStyle="Regular" PointSize="12" CharacterAki="0" LineAki="9" HorizontalScale="100" VerticalScale="100" LineAlignment="LeftOrTopLineJustify" GridAlignment="AlignEmCenter" CharacterAlignment="AlignEmCenter">
				<Properties>
					<AppliedFont type="string">Minion Pro</AppliedFont>
				</Properties>
			</GridDataInformation>
			<Guide Self="u8e1" OverriddenPageItemProps="" Orientation="Horizontal" Location="504.60000000000036" FitToPage="true" ViewThreshold="5" Locked="false" ItemLayer="uc4" PageIndex="-1" GuideType="Ruler" GuideZone="1">
				<Properties>
					<GuideColor type="enumeration">Cyan</GuideColor>
				</Properties>
			</Guide>
		</Page>
		<Page Self="u169" Name="11" AppliedTrapPreset="TrapPreset/$ID/kDefaultTrapStyleName" GeometricBounds="0 0 612 792" ItemTransform="1 0 0 1 0 -306" AppliedAlternateLayout="ucd" LayoutRule="UseMaster" SnapshotBlendingMode="IgnoreLayoutSnapshots" OptionalPage="false" AppliedMaster="uce" OverrideList="" MasterPageTransform="1 0 0 1 90 -90" TabOrder="" GridStartingPoint="TopOutside" UseMasterGrid="false">
			<Properties>
				<PageColor type="enumeration">UseMasterColor</PageColor>
				<Descriptor type="list">
					<ListItem type="string"></ListItem>
					<ListItem type="enumeration">Arabic</ListItem>
					<ListItem type="boolean">true</ListItem>
					<ListItem type="boolean">false</ListItem>
					<ListItem type="long">11</ListItem>
					<ListItem type="string"></ListItem>
				</Descriptor>
			</Properties>
			<MarginPreference ColumnCount="1" ColumnGutter="12" Top="36" Bottom="36" Left="36" Right="36" ColumnDirection="Horizontal" ColumnsPositions="0 720" />
			<GridDataInformation FontStyle="Regular" PointSize="12" CharacterAki="0" LineAki="9" HorizontalScale="100" VerticalScale="100" LineAlignment="LeftOrTopLineJustify" GridAlignment="AlignEmCenter" CharacterAlignment="AlignEmCenter">
				<Properties>
					<AppliedFont type="string">Minion Pro</AppliedFont>
				</Properties>
			</GridDataInformation>
			<Guide Self="u8e4" OverriddenPageItemProps="" Orientation="Horizontal" Location="504.60000000000036" FitToPage="true" ViewThreshold="5" Locked="false" ItemLayer="uc4" PageIndex="1" GuideType="Ruler" GuideZone="1">
				<Properties>
					<GuideColor type="enumeration">Cyan</GuideColor>
				</Properties>
			</Guide>
		</Page>
		<Rectangle Self="u2f5" ContentType="GraphicType" StoryTitle="$ID/" ParentInterfaceChangeCount="" TargetInterfaceChangeCount="" LastUpdatedInterfaceChangeCount="" OverriddenPageItemProps="" Visible="true" Name="$ID/" HorizontalLayoutConstraints="FlexibleDimension FixedDimension FlexibleDimension" VerticalLayoutConstraints="FlexibleDimension FixedDimension FlexibleDimension" GradientFillStart="0 0" GradientFillLength="0" GradientFillAngle="0" GradientStrokeStart="0 0" GradientStrokeLength="0" GradientStrokeAngle="0" ItemLayer="uc4" Locked="false" LocalDisplaySetting="Default" GradientFillHiliteLength="0" GradientFillHiliteAngle="0" GradientStrokeHiliteLength="0" GradientStrokeHiliteAngle="0" AppliedObjectStyle="ObjectStyle/$ID/[None]" ItemTransform="1 0 0 1 -310.59999999999997 -53.61944645729497">
			<Properties>
				<PathGeometry>
					<GeometryPathType PathOpen="false">
						<PathPointArray>
							<PathPointType Anchor="-481.2 -260.4" LeftDirection="-481.2 -260.4" RightDirection="-481.2 -260.4" />
							<PathPointType Anchor="-481.2 267.6000000000001" LeftDirection="-481.2 267.6000000000001" RightDirection="-481.2 267.6000000000001" />
							<PathPointType Anchor="310.79999999999995 267.6000000000001" LeftDirection="310.79999999999995 267.6000000000001" RightDirection="310.79999999999995 267.6000000000001" />
							<PathPointType Anchor="310.79999999999995 -260.4" LeftDirection="310.79999999999995 -260.4" RightDirection="310.79999999999995 -260.4" />
						</PathPointArray>
					</GeometryPathType>
				</PathGeometry>
			</Properties>
			<TextWrapPreference Inverse="false" ApplyToMasterPageOnly="false" TextWrapSide="BothSides" TextWrapMode="None">
				<Properties>
					<TextWrapOffset Top="0" Left="0" Bottom="0" Right="0" />
				</Properties>
				<ContourOption ContourType="SameAsClipping" IncludeInsideEdges="false" ContourPathName="$ID/" />
			</TextWrapPreference>
			<InCopyExportOption IncludeGraphicProxies="true" IncludeAllResources="false" />
			<FrameFittingOption TopCrop="4.363783685282158" BottomCrop="-4.363783685282328" FittingOnEmptyFrame="ContentToFrame" />
			<ObjectExportOption AltTextSourceType="SourceXMLStructure" ActualTextSourceType="SourceXMLStructure" CustomAltText="$ID/" CustomActualText="$ID/" ApplyTagType="TagFromStructure" ImageConversionType="JPEG" ImageExportResolution="Ppi300" GIFOptionsPalette="AdaptivePalette" GIFOptionsInterlaced="true" JPEGOptionsQuality="High" JPEGOptionsFormat="BaselineEncoding" ImageAlignment="AlignLeft" ImageSpaceBefore="0" ImageSpaceAfter="0" UseImagePageBreak="false" ImagePageBreak="PageBreakBefore" CustomImageAlignment="false" SpaceUnit="CssPixel" CustomLayout="false" CustomLayoutType="AlignmentAndSpacing" EpubType="$ID/" SizeType="DefaultSize" CustomSize="$ID/" PreserveAppearanceFromLayout="PreserveAppearanceDefault">
				<Properties>
					<AltMetadataProperty NamespacePrefix="$ID/" PropertyPath="$ID/" />
					<ActualMetadataProperty NamespacePrefix="$ID/" PropertyPath="$ID/" />
				</Properties>
			</ObjectExportOption>
			<Image Self="u9bd" Space="$ID/#Links_RGB" ActualPpi="320 320" EffectivePpi="349 349" ImageRenderingIntent="UseColorSettings" OverriddenPageItemProps="" LocalDisplaySetting="Default" ImageTypeName="$ID/Portable Network Graphics (PNG)" AppliedObjectStyle="ObjectStyle/$ID/[None]" ItemTransform="0.9166357199350993 0 0 0.9166357199350993 -481.20000000000005 -264.39999999999964" ParentInterfaceChangeCount="" TargetInterfaceChangeCount="" LastUpdatedInterfaceChangeCount="" Visible="true" Name="$ID/" HorizontalLayoutConstraints="FlexibleDimension FixedDimension FlexibleDimension" VerticalLayoutConstraints="FlexibleDimension FixedDimension FlexibleDimension" GradientFillStart="0 0" GradientFillLength="0" GradientFillAngle="0" GradientFillHiliteLength="0" GradientFillHiliteAngle="0">
				<Properties>
					<Profile type="string">$ID/None</Profile>
					<GraphicBounds Left="0" Top="0" Right="864.0291696859425" Bottom="576.019446457295" />
				</Properties>
				<TextWrapPreference Inverse="false" ApplyToMasterPageOnly="false" TextWrapSide="BothSides" TextWrapMode="None">
					<Properties>
						<TextWrapOffset Top="0" Left="0" Bottom="0" Right="0" />
					</Properties>
					<ContourOption ContourType="SameAsClipping" IncludeInsideEdges="false" ContourPathName="$ID/" />
				</TextWrapPreference>
				<MetadataPacketPreference>
					<Properties>
						<Contents><![CDATA[<?xpacket begin="﻿" id="W5M0MpCehiHzreSzNTczkc9d"?>
<x:xmpmeta xmlns:x="adobe:ns:meta/" x:xmptk="Adobe XMP Core 5.6-c145 79.163499, 2018/08/13-16:40:22        ">
   <rdf:RDF xmlns:rdf="http://www.w3.org/1999/02/22-rdf-syntax-ns#">
      <rdf:Description rdf:about=""
            xmlns:xmp="http://ns.adobe.com/xap/1.0/"
            xmlns:dc="http://purl.org/dc/elements/1.1/"
            xmlns:photoshop="http://ns.adobe.com/photoshop/1.0/"
            xmlns:xmpMM="http://ns.adobe.com/xap/1.0/mm/"
            xmlns:stEvt="http://ns.adobe.com/xap/1.0/sType/ResourceEvent#"
            xmlns:tiff="http://ns.adobe.com/tiff/1.0/"
            xmlns:exif="http://ns.adobe.com/exif/1.0/">
         <xmp:CreatorTool>Adobe Photoshop CC 2015 (Macintosh)</xmp:CreatorTool>
         <xmp:CreateDate>2016-05-06T11:07:27-07:00</xmp:CreateDate>
         <xmp:ModifyDate>2016-05-26T15:14:05-07:00</xmp:ModifyDate>
         <xmp:MetadataDate>2016-05-26T15:14:05-07:00</xmp:MetadataDate>
         <dc:format>image/png</dc:format>
         <photoshop:ColorMode>3</photoshop:ColorMode>
         <xmpMM:InstanceID>xmp.iid:c9c4ec50-ce17-4edf-bf72-6ed4f3b2f02f</xmpMM:InstanceID>
         <xmpMM:DocumentID>xmp.did:c9c4ec50-ce17-4edf-bf72-6ed4f3b2f02f</xmpMM:DocumentID>
         <xmpMM:OriginalDocumentID>xmp.did:c9c4ec50-ce17-4edf-bf72-6ed4f3b2f02f</xmpMM:OriginalDocumentID>
         <xmpMM:History>
            <rdf:Seq>
               <rdf:li rdf:parseType="Resource">
                  <stEvt:action>created</stEvt:action>
                  <stEvt:instanceID>xmp.iid:c9c4ec50-ce17-4edf-bf72-6ed4f3b2f02f</stEvt:instanceID>
                  <stEvt:when>2016-05-06T11:07:27-07:00</stEvt:when>
                  <stEvt:softwareAgent>Adobe Photoshop CC 2015 (Macintosh)</stEvt:softwareAgent>
               </rdf:li>
            </rdf:Seq>
         </xmpMM:History>
         <tiff:Orientation>1</tiff:Orientation>
         <tiff:XResolution>3200000/10000</tiff:XResolution>
         <tiff:YResolution>3200000/10000</tiff:YResolution>
         <tiff:ResolutionUnit>2</tiff:ResolutionUnit>
         <exif:ColorSpace>65535</exif:ColorSpace>
         <exif:PixelXDimension>3840</exif:PixelXDimension>
         <exif:PixelYDimension>2560</exif:PixelYDimension>
      </rdf:Description>
   </rdf:RDF>
</x:xmpmeta>
<?xpacket end="r"?>]]></Contents>
					</Properties>
				</MetadataPacketPreference>
				<Link Self="u8c1" AssetURL="$ID/" AssetID="$ID/" LinkResourceURI="file:/Users/admin/OneDrive%20-%20Microsoft/The%20Illustrated%20Guide%20to%20Kubernetes%20MSFT%20Edition/The%20Illustrated%20Children%27s%20Guide%20to%20Kubernetes%20-%20CNCF/The%20Illustrated%20Childrens%20Guide%20to%20Kubernetes%20Book%20Files%20-%20Sept%202018%20-%20CNCF%20Folder/Links/page5.png" LinkResourceFormat="$ID/Portable Network Graphics (PNG)" StoredState="Normal" LinkClassID="35906" LinkClientID="257" LinkResourceModified="false" LinkObjectModified="false" ShowInUI="true" CanEmbed="true" CanUnembed="true" CanPackage="true" ImportPolicy="NoAutoImport" ExportPolicy="NoAutoExport" LinkImportStamp="file 131426651420000000 3519169" LinkImportModificationTime="2017-06-22T21:19:02" LinkImportTime="2017-08-16T16:09:13" LinkResourceSize="0~35b2c1" RenditionData="Actual" />
				<ClippingPathSettings ClippingType="None" InvertPath="false" IncludeInsideEdges="false" RestrictToFrame="false" UseHighResolutionImage="true" Threshold="25" Tolerance="2" InsetFrame="0" AppliedPathName="$ID/" Index="-1" />
				<ImageIOPreference ApplyPhotoshopClippingPath="true" AllowAutoEmbedding="true" AlphaChannelName="$ID/" />
			</Image>
		</Rectangle>
		<Rectangle Self="u2f9" ContentType="Unassigned" StoryTitle="$ID/" ParentInterfaceChangeCount="" TargetInterfaceChangeCount="" LastUpdatedInterfaceChangeCount="" OverriddenPageItemProps="" Visible="true" Name="$ID/" HorizontalLayoutConstraints="FlexibleDimension FixedDimension FlexibleDimension" VerticalLayoutConstraints="FlexibleDimension FixedDimension FlexibleDimension" FillColor="Color/Paper" StrokeWeight="0" StrokeColor="Swatch/None" GradientFillStart="0 0" GradientFillLength="0" GradientFillAngle="0" GradientStrokeStart="0 0" GradientStrokeLength="0" GradientStrokeAngle="0" ItemLayer="uc4" Locked="false" LocalDisplaySetting="Default" GradientFillHiliteLength="0" GradientFillHiliteAngle="0" GradientStrokeHiliteLength="0" GradientStrokeHiliteAngle="0" AppliedObjectStyle="ObjectStyle/$ID/[Normal Graphics Frame]" ItemTransform="1 0 0 1 -395.79999999999995 -74.01944645729509">
			<Properties>
				<PathGeometry>
					<GeometryPathType PathOpen="false">
						<PathPointArray>
							<PathPointType Anchor="-396.00000000000006 190.8" LeftDirection="-396.00000000000006 190.8" RightDirection="-396.00000000000006 190.8" />
							<PathPointType Anchor="-396.00000000000006 306" LeftDirection="-396.00000000000006 306" RightDirection="-396.00000000000006 306" />
							<PathPointType Anchor="396 306" LeftDirection="396 306" RightDirection="396 306" />
							<PathPointType Anchor="396 190.8" LeftDirection="396 190.8" RightDirection="396 190.8" />
						</PathPointArray>
					</GeometryPathType>
				</PathGeometry>
			</Properties>
			<TransparencySetting>
				<GradientFeatherSetting Applied="true" Angle="90" Length="115.19999999999999" GradientStart="-396.00000000000006 306">
					<OpacityGradientStop Self="u2f9TransparencySetting1GradientFeatherSetting1OpacityGradientStop0" Opacity="100" Location="18.865" />
					<OpacityGradientStop Self="u2f9TransparencySetting1GradientFeatherSetting1OpacityGradientStop1" Opacity="0" Location="98.055" Midpoint="72.07349412804646" />
				</GradientFeatherSetting>
			</TransparencySetting>
			<TextWrapPreference Inverse="false" ApplyToMasterPageOnly="false" TextWrapSide="BothSides" TextWrapMode="None">
				<Properties>
					<TextWrapOffset Top="0" Left="0" Bottom="0" Right="0" />
				</Properties>
			</TextWrapPreference>
			<InCopyExportOption IncludeGraphicProxies="true" IncludeAllResources="false" />
			<FrameFittingOption AutoFit="false" LeftCrop="0" TopCrop="0" RightCrop="0" BottomCrop="0" FittingOnEmptyFrame="None" FittingAlignment="CenterAnchor" />
			<ObjectExportOption AltTextSourceType="SourceXMLStructure" ActualTextSourceType="SourceXMLStructure" CustomAltText="$ID/" CustomActualText="$ID/" ApplyTagType="TagFromStructure" ImageConversionType="JPEG" ImageExportResolution="Ppi300" GIFOptionsPalette="AdaptivePalette" GIFOptionsInterlaced="true" JPEGOptionsQuality="High" JPEGOptionsFormat="BaselineEncoding" ImageAlignment="AlignLeft" ImageSpaceBefore="0" ImageSpaceAfter="0" UseImagePageBreak="false" ImagePageBreak="PageBreakBefore" CustomImageAlignment="false" SpaceUnit="CssPixel" CustomLayout="false" CustomLayoutType="AlignmentAndSpacing" EpubType="$ID/" SizeType="DefaultSize" CustomSize="$ID/" PreserveAppearanceFromLayout="PreserveAppearanceDefault">
				<Properties>
					<AltMetadataProperty NamespacePrefix="$ID/" PropertyPath="$ID/" />
					<ActualMetadataProperty NamespacePrefix="$ID/" PropertyPath="$ID/" />
				</Properties>
			</ObjectExportOption>
		</Rectangle>
		<TextFrame Self="u2fa" ParentStory="u2fd" PreviousTextFrame="n" NextTextFrame="n" ContentType="TextType" ParentInterfaceChangeCount="" TargetInterfaceChangeCount="" LastUpdatedInterfaceChangeCount="" OverriddenPageItemProps="" Visible="true" Name="$ID/" HorizontalLayoutConstraints="FlexibleDimension FixedDimension FlexibleDimension" VerticalLayoutConstraints="FlexibleDimension FixedDimension FlexibleDimension" GradientFillStart="0 0" GradientFillLength="0" GradientFillAngle="0" GradientStrokeStart="0 0" GradientStrokeLength="0" GradientStrokeAngle="0" ItemLayer="uc4" Locked="false" LocalDisplaySetting="Default" GradientFillHiliteLength="0" GradientFillHiliteAngle="0" GradientStrokeHiliteLength="0" GradientStrokeHiliteAngle="0" AppliedObjectStyle="ObjectStyle/$ID/[None]" ItemTransform="1 0 0 1 -396 -2378.3999999999996">
			<Properties>
				<PathGeometry>
					<GeometryPathType PathOpen="false">
						<PathPointArray>
							<PathPointType Anchor="-360 2565" LeftDirection="-360 2565" RightDirection="-360 2565" />
							<PathPointType Anchor="-360 2644.6" LeftDirection="-360 2644.6" RightDirection="-360 2644.6" />
							<PathPointType Anchor="360 2644.6" LeftDirection="360 2644.6" RightDirection="360 2644.6" />
							<PathPointType Anchor="360 2565" LeftDirection="360 2565" RightDirection="360 2565" />
						</PathPointArray>
					</GeometryPathType>
				</PathGeometry>
			</Properties>
			<TextFramePreference FootnotesEnableOverrides="false" FootnotesSpanAcrossColumns="false" FootnotesMinimumSpacing="12" FootnotesSpaceBetween="6" TextColumnCount="1" TextColumnFixedWidth="720" TextColumnMaxWidth="0">
				<Properties>
					<InsetSpacing type="list">
						<ListItem type="unit">0</ListItem>
						<ListItem type="unit">0</ListItem>
						<ListItem type="unit">0</ListItem>
						<ListItem type="unit">0</ListItem>
					</InsetSpacing>
				</Properties>
			</TextFramePreference>
			<TextFrameFootnoteOptionsObject EnableOverrides="false" SpanFootnotesAcross="false" MinimumSpacingOption="12" SpaceBetweenFootnotes="6" />
			<TextWrapPreference Inverse="false" ApplyToMasterPageOnly="false" TextWrapSide="BothSides" TextWrapMode="None">
				<Properties>
					<TextWrapOffset Top="0" Left="0" Bottom="0" Right="0" />
				</Properties>
			</TextWrapPreference>
			<ObjectExportOption AltTextSourceType="SourceXMLStructure" ActualTextSourceType="SourceXMLStructure" CustomAltText="$ID/" CustomActualText="$ID/" ApplyTagType="TagFromStructure" ImageConversionType="JPEG" ImageExportResolution="Ppi300" GIFOptionsPalette="AdaptivePalette" GIFOptionsInterlaced="true" JPEGOptionsQuality="High" JPEGOptionsFormat="BaselineEncoding" ImageAlignment="AlignLeft" ImageSpaceBefore="0" ImageSpaceAfter="0" UseImagePageBreak="false" ImagePageBreak="PageBreakBefore" CustomImageAlignment="false" SpaceUnit="CssPixel" CustomLayout="false" CustomLayoutType="AlignmentAndSpacing" EpubType="$ID/" SizeType="DefaultSize" CustomSize="$ID/" PreserveAppearanceFromLayout="PreserveAppearanceDefault">
				<Properties>
					<AltMetadataProperty NamespacePrefix="$ID/" PropertyPath="$ID/" />
					<ActualMetadataProperty NamespacePrefix="$ID/" PropertyPath="$ID/" />
				</Properties>
			</ObjectExportOption>
		</TextFrame>
		<Rectangle Self="u31c" ContentType="GraphicType" StoryTitle="$ID/" ParentInterfaceChangeCount="" TargetInterfaceChangeCount="" LastUpdatedInterfaceChangeCount="" OverriddenPageItemProps="" Visible="true" Name="$ID/" HorizontalLayoutConstraints="FlexibleDimension FixedDimension FlexibleDimension" VerticalLayoutConstraints="FlexibleDimension FixedDimension FlexibleDimension" GradientFillStart="0 0" GradientFillLength="0" GradientFillAngle="0" GradientStrokeStart="0 0" GradientStrokeLength="0" GradientStrokeAngle="0" ItemLayer="uc4" Locked="false" LocalDisplaySetting="Default" GradientFillHiliteLength="0" GradientFillHiliteAngle="0" GradientStrokeHiliteLength="0" GradientStrokeHiliteAngle="0" AppliedObjectStyle="ObjectStyle/$ID/[None]" ItemTransform="1 0 0 1 481.4000000000001 -45.61944645729497">
			<Properties>
				<PathGeometry>
					<GeometryPathType PathOpen="false">
						<PathPointArray>
							<PathPointType Anchor="-481.2 -260.4" LeftDirection="-481.2 -260.4" RightDirection="-481.2 -260.4" />
							<PathPointType Anchor="-481.2 267.6000000000001" LeftDirection="-481.2 267.6000000000001" RightDirection="-481.2 267.6000000000001" />
							<PathPointType Anchor="310.79999999999995 267.6000000000001" LeftDirection="310.79999999999995 267.6000000000001" RightDirection="310.79999999999995 267.6000000000001" />
							<PathPointType Anchor="310.79999999999995 -260.4" LeftDirection="310.79999999999995 -260.4" RightDirection="310.79999999999995 -260.4" />
						</PathPointArray>
					</GeometryPathType>
				</PathGeometry>
			</Properties>
			<TextWrapPreference Inverse="false" ApplyToMasterPageOnly="false" TextWrapSide="BothSides" TextWrapMode="None">
				<Properties>
					<TextWrapOffset Top="0" Left="0" Bottom="0" Right="0" />
				</Properties>
				<ContourOption ContourType="SameAsClipping" IncludeInsideEdges="false" ContourPathName="$ID/" />
			</TextWrapPreference>
			<InCopyExportOption IncludeGraphicProxies="true" IncludeAllResources="false" />
			<FrameFittingOption FittingOnEmptyFrame="ContentToFrame" />
			<ObjectExportOption AltTextSourceType="SourceXMLStructure" ActualTextSourceType="SourceXMLStructure" CustomAltText="$ID/" CustomActualText="$ID/" ApplyTagType="TagFromStructure" ImageConversionType="JPEG" ImageExportResolution="Ppi300" GIFOptionsPalette="AdaptivePalette" GIFOptionsInterlaced="true" JPEGOptionsQuality="High" JPEGOptionsFormat="BaselineEncoding" ImageAlignment="AlignLeft" ImageSpaceBefore="0" ImageSpaceAfter="0" UseImagePageBreak="false" ImagePageBreak="PageBreakBefore" CustomImageAlignment="false" SpaceUnit="CssPixel" CustomLayout="false" CustomLayoutType="AlignmentAndSpacing" EpubType="$ID/" SizeType="DefaultSize" CustomSize="$ID/" PreserveAppearanceFromLayout="PreserveAppearanceDefault">
				<Properties>
					<AltMetadataProperty NamespacePrefix="$ID/" PropertyPath="$ID/" />
					<ActualMetadataProperty NamespacePrefix="$ID/" PropertyPath="$ID/" />
				</Properties>
			</ObjectExportOption>
			<Image Self="u95d" Space="$ID/#Links_RGB" ActualPpi="320 320" EffectivePpi="349 349" ImageRenderingIntent="UseColorSettings" OverriddenPageItemProps="" LocalDisplaySetting="Default" ImageTypeName="$ID/Portable Network Graphics (PNG)" AppliedObjectStyle="ObjectStyle/$ID/[None]" ItemTransform="0.9166357199350993 0 0 0.9166357199350994 -481.20000000000005 -260.4" ParentInterfaceChangeCount="" TargetInterfaceChangeCount="" LastUpdatedInterfaceChangeCount="" Visible="true" Name="$ID/" HorizontalLayoutConstraints="FlexibleDimension FixedDimension FlexibleDimension" VerticalLayoutConstraints="FlexibleDimension FixedDimension FlexibleDimension" GradientFillStart="0 0" GradientFillLength="0" GradientFillAngle="0" GradientFillHiliteLength="0" GradientFillHiliteAngle="0">
				<Properties>
					<Profile type="string">$ID/None</Profile>
					<GraphicBounds Left="0" Top="0" Right="864.0291696859425" Bottom="576.019446457295" />
				</Properties>
				<TextWrapPreference Inverse="false" ApplyToMasterPageOnly="false" TextWrapSide="BothSides" TextWrapMode="None">
					<Properties>
						<TextWrapOffset Top="0" Left="0" Bottom="0" Right="0" />
					</Properties>
					<ContourOption ContourType="SameAsClipping" IncludeInsideEdges="false" ContourPathName="$ID/" />
				</TextWrapPreference>
				<MetadataPacketPreference>
					<Properties>
						<Contents><![CDATA[<?xpacket begin="﻿" id="W5M0MpCehiHzreSzNTczkc9d"?>
<x:xmpmeta xmlns:x="adobe:ns:meta/" x:xmptk="Adobe XMP Core 5.6-c145 79.163499, 2018/08/13-16:40:22        ">
   <rdf:RDF xmlns:rdf="http://www.w3.org/1999/02/22-rdf-syntax-ns#">
      <rdf:Description rdf:about=""
            xmlns:xmp="http://ns.adobe.com/xap/1.0/"
            xmlns:dc="http://purl.org/dc/elements/1.1/"
            xmlns:photoshop="http://ns.adobe.com/photoshop/1.0/"
            xmlns:xmpMM="http://ns.adobe.com/xap/1.0/mm/"
            xmlns:stEvt="http://ns.adobe.com/xap/1.0/sType/ResourceEvent#"
            xmlns:stRef="http://ns.adobe.com/xap/1.0/sType/ResourceRef#"
            xmlns:tiff="http://ns.adobe.com/tiff/1.0/"
            xmlns:exif="http://ns.adobe.com/exif/1.0/">
         <xmp:CreatorTool>Adobe Photoshop CC 2015 (Macintosh)</xmp:CreatorTool>
         <xmp:CreateDate>2016-03-29T20:43:42-07:00</xmp:CreateDate>
         <xmp:ModifyDate>2016-05-10T15:29:45-07:00</xmp:ModifyDate>
         <xmp:MetadataDate>2016-05-10T15:29:45-07:00</xmp:MetadataDate>
         <dc:format>image/png</dc:format>
         <photoshop:ColorMode>3</photoshop:ColorMode>
         <photoshop:TextLayers>
            <rdf:Bag>
               <rdf:li rdf:parseType="Resource">
                  <photoshop:LayerName>Kubernetes</photoshop:LayerName>
                  <photoshop:LayerText>Kubernetes</photoshop:LayerText>
               </rdf:li>
               <rdf:li rdf:parseType="Resource">
                  <photoshop:LayerName>• Phi-Beta-Kappa: Philsophia Biou    Kubernetes (Love of Wisdom</photoshop:LayerName>
                  <photoshop:LayerText>• Phi-Beta-Kappa: Philsophia Biou    Kubernetes (Love of Wisdom Pilots     life)</photoshop:LayerText>
               </rdf:li>
            </rdf:Bag>
         </photoshop:TextLayers>
         <photoshop:DocumentAncestors>
            <rdf:Bag>
               <rdf:li>adobe:docid:photoshop:1389d92e-3748-1179-a0cb-c1f06562f7f4</rdf:li>
            </rdf:Bag>
         </photoshop:DocumentAncestors>
         <xmpMM:InstanceID>xmp.iid:f9e776e7-87da-46e3-a313-d9f1863aabe2</xmpMM:InstanceID>
         <xmpMM:DocumentID>adobe:docid:photoshop:177bb532-578d-1179-b53d-ecadfdcef1ee</xmpMM:DocumentID>
         <xmpMM:OriginalDocumentID>xmp.did:0a025908-c097-4ca9-9766-f4e37952ec1e</xmpMM:OriginalDocumentID>
         <xmpMM:History>
            <rdf:Seq>
               <rdf:li rdf:parseType="Resource">
                  <stEvt:action>created</stEvt:action>
                  <stEvt:instanceID>xmp.iid:0a025908-c097-4ca9-9766-f4e37952ec1e</stEvt:instanceID>
                  <stEvt:when>2016-03-29T20:43:42-07:00</stEvt:when>
                  <stEvt:softwareAgent>Adobe Photoshop CC 2015 (Macintosh)</stEvt:softwareAgent>
               </rdf:li>
               <rdf:li rdf:parseType="Resource">
                  <stEvt:action>converted</stEvt:action>
                  <stEvt:parameters>from image/png to application/vnd.adobe.photoshop</stEvt:parameters>
               </rdf:li>
               <rdf:li rdf:parseType="Resource">
                  <stEvt:action>saved</stEvt:action>
                  <stEvt:instanceID>xmp.iid:2ab65d78-a3f4-48af-a6f2-1bd24caa4561</stEvt:instanceID>
                  <stEvt:when>2016-03-30T14:27:22-07:00</stEvt:when>
                  <stEvt:softwareAgent>Adobe Photoshop CC 2015 (Macintosh)</stEvt:softwareAgent>
                  <stEvt:changed>/</stEvt:changed>
               </rdf:li>
               <rdf:li rdf:parseType="Resource">
                  <stEvt:action>saved</stEvt:action>
                  <stEvt:instanceID>xmp.iid:5fde2c8b-ba6c-47fd-98fc-72be957211ba</stEvt:instanceID>
                  <stEvt:when>2016-05-10T15:29:45-07:00</stEvt:when>
                  <stEvt:softwareAgent>Adobe Photoshop CC 2015 (Macintosh)</stEvt:softwareAgent>
                  <stEvt:changed>/</stEvt:changed>
               </rdf:li>
               <rdf:li rdf:parseType="Resource">
                  <stEvt:action>converted</stEvt:action>
                  <stEvt:parameters>from application/vnd.adobe.photoshop to image/png</stEvt:parameters>
               </rdf:li>
               <rdf:li rdf:parseType="Resource">
                  <stEvt:action>derived</stEvt:action>
                  <stEvt:parameters>converted from application/vnd.adobe.photoshop to image/png</stEvt:parameters>
               </rdf:li>
               <rdf:li rdf:parseType="Resource">
                  <stEvt:action>saved</stEvt:action>
                  <stEvt:instanceID>xmp.iid:f9e776e7-87da-46e3-a313-d9f1863aabe2</stEvt:instanceID>
                  <stEvt:when>2016-05-10T15:29:45-07:00</stEvt:when>
                  <stEvt:softwareAgent>Adobe Photoshop CC 2015 (Macintosh)</stEvt:softwareAgent>
                  <stEvt:changed>/</stEvt:changed>
               </rdf:li>
            </rdf:Seq>
         </xmpMM:History>
         <xmpMM:DerivedFrom rdf:parseType="Resource">
            <stRef:instanceID>xmp.iid:5fde2c8b-ba6c-47fd-98fc-72be957211ba</stRef:instanceID>
            <stRef:documentID>adobe:docid:photoshop:1389d92e-3748-1179-a0cb-c1f06562f7f4</stRef:documentID>
            <stRef:originalDocumentID>xmp.did:0a025908-c097-4ca9-9766-f4e37952ec1e</stRef:originalDocumentID>
         </xmpMM:DerivedFrom>
         <tiff:Orientation>1</tiff:Orientation>
         <tiff:XResolution>3200000/10000</tiff:XResolution>
         <tiff:YResolution>3200000/10000</tiff:YResolution>
         <tiff:ResolutionUnit>2</tiff:ResolutionUnit>
         <exif:ColorSpace>65535</exif:ColorSpace>
         <exif:PixelXDimension>3840</exif:PixelXDimension>
         <exif:PixelYDimension>2560</exif:PixelYDimension>
      </rdf:Description>
   </rdf:RDF>
</x:xmpmeta>
<?xpacket end="r"?>]]></Contents>
					</Properties>
				</MetadataPacketPreference>
				<Link Self="u33f" AssetURL="$ID/" AssetID="$ID/" LinkResourceURI="file:/Users/admin/OneDrive%20-%20Microsoft/The%20Illustrated%20Guide%20to%20Kubernetes%20MSFT%20Edition/The%20Illustrated%20Children%27s%20Guide%20to%20Kubernetes%20-%20CNCF/The%20Illustrated%20Childrens%20Guide%20to%20Kubernetes%20Book%20Files%20-%20Sept%202018%20-%20CNCF%20Folder/Links/diagram4.png" LinkResourceFormat="$ID/Portable Network Graphics (PNG)" StoredState="Normal" LinkClassID="35906" LinkClientID="257" LinkResourceModified="false" LinkObjectModified="false" ShowInUI="true" CanEmbed="true" CanUnembed="true" CanPackage="true" ImportPolicy="NoAutoImport" ExportPolicy="NoAutoExport" LinkImportStamp="file 131426651810000000 1498133" LinkImportModificationTime="2017-06-22T21:19:41" LinkImportTime="2017-08-16T16:09:10" LinkResourceSize="0~16dc15" RenditionData="Actual" />
				<ClippingPathSettings ClippingType="None" InvertPath="false" IncludeInsideEdges="false" RestrictToFrame="false" UseHighResolutionImage="true" Threshold="25" Tolerance="2" InsetFrame="0" AppliedPathName="$ID/" Index="-1" />
				<ImageIOPreference ApplyPhotoshopClippingPath="true" AllowAutoEmbedding="true" AlphaChannelName="$ID/" />
			</Image>
		</Rectangle>
		<Rectangle Self="u322" ContentType="Unassigned" StoryTitle="$ID/" ParentInterfaceChangeCount="" TargetInterfaceChangeCount="" LastUpdatedInterfaceChangeCount="" OverriddenPageItemProps="" Visible="true" Name="$ID/" HorizontalLayoutConstraints="FlexibleDimension FixedDimension FlexibleDimension" VerticalLayoutConstraints="FlexibleDimension FixedDimension FlexibleDimension" FillColor="Color/Paper" StrokeWeight="0" StrokeColor="Swatch/None" GradientFillStart="0 0" GradientFillLength="0" GradientFillAngle="0" GradientStrokeStart="0 0" GradientStrokeLength="0" GradientStrokeAngle="0" ItemLayer="uc4" Locked="false" LocalDisplaySetting="Default" GradientFillHiliteLength="0" GradientFillHiliteAngle="0" GradientStrokeHiliteLength="0" GradientStrokeHiliteAngle="0" AppliedObjectStyle="ObjectStyle/$ID/[Normal Graphics Frame]" ItemTransform="1 0 0 1 396.20000000000005 -74.01944645729509">
			<Properties>
				<PathGeometry>
					<GeometryPathType PathOpen="false">
						<PathPointArray>
							<PathPointType Anchor="-396.00000000000006 190.8" LeftDirection="-396.00000000000006 190.8" RightDirection="-396.00000000000006 190.8" />
							<PathPointType Anchor="-396.00000000000006 306" LeftDirection="-396.00000000000006 306" RightDirection="-396.00000000000006 306" />
							<PathPointType Anchor="396 306" LeftDirection="396 306" RightDirection="396 306" />
							<PathPointType Anchor="396 190.8" LeftDirection="396 190.8" RightDirection="396 190.8" />
						</PathPointArray>
					</GeometryPathType>
				</PathGeometry>
			</Properties>
			<TransparencySetting>
				<GradientFeatherSetting Applied="true" Angle="90" Length="115.19999999999999" GradientStart="-396.00000000000006 306">
					<OpacityGradientStop Self="u322TransparencySetting1GradientFeatherSetting1OpacityGradientStop0" Opacity="100" Location="18.865" />
					<OpacityGradientStop Self="u322TransparencySetting1GradientFeatherSetting1OpacityGradientStop1" Opacity="0" Location="98.055" Midpoint="72.07349412804646" />
				</GradientFeatherSetting>
			</TransparencySetting>
			<TextWrapPreference Inverse="false" ApplyToMasterPageOnly="false" TextWrapSide="BothSides" TextWrapMode="None">
				<Properties>
					<TextWrapOffset Top="0" Left="0" Bottom="0" Right="0" />
				</Properties>
			</TextWrapPreference>
			<InCopyExportOption IncludeGraphicProxies="true" IncludeAllResources="false" />
			<FrameFittingOption AutoFit="false" LeftCrop="0" TopCrop="0" RightCrop="0" BottomCrop="0" FittingOnEmptyFrame="None" FittingAlignment="CenterAnchor" />
			<ObjectExportOption AltTextSourceType="SourceXMLStructure" ActualTextSourceType="SourceXMLStructure" CustomAltText="$ID/" CustomActualText="$ID/" ApplyTagType="TagFromStructure" ImageConversionType="JPEG" ImageExportResolution="Ppi300" GIFOptionsPalette="AdaptivePalette" GIFOptionsInterlaced="true" JPEGOptionsQuality="High" JPEGOptionsFormat="BaselineEncoding" ImageAlignment="AlignLeft" ImageSpaceBefore="0" ImageSpaceAfter="0" UseImagePageBreak="false" ImagePageBreak="PageBreakBefore" CustomImageAlignment="false" SpaceUnit="CssPixel" CustomLayout="false" CustomLayoutType="AlignmentAndSpacing" EpubType="$ID/" SizeType="DefaultSize" CustomSize="$ID/" PreserveAppearanceFromLayout="PreserveAppearanceDefault">
				<Properties>
					<AltMetadataProperty NamespacePrefix="$ID/" PropertyPath="$ID/" />
					<ActualMetadataProperty NamespacePrefix="$ID/" PropertyPath="$ID/" />
				</Properties>
			</ObjectExportOption>
		</Rectangle>
		<TextFrame Self="u47d" ParentStory="u480" PreviousTextFrame="n" NextTextFrame="n" ContentType="TextType" ParentInterfaceChangeCount="" TargetInterfaceChangeCount="" LastUpdatedInterfaceChangeCount="" OverriddenPageItemProps="" Visible="true" Name="$ID/" HorizontalLayoutConstraints="FlexibleDimension FixedDimension FlexibleDimension" VerticalLayoutConstraints="FlexibleDimension FixedDimension FlexibleDimension" GradientFillStart="0 0" GradientFillLength="0" GradientFillAngle="0" GradientStrokeStart="0 0" GradientStrokeLength="0" GradientStrokeAngle="0" ItemLayer="uc4" Locked="false" LocalDisplaySetting="Default" GradientFillHiliteLength="0" GradientFillHiliteAngle="0" GradientStrokeHiliteLength="0" GradientStrokeHiliteAngle="0" AppliedObjectStyle="ObjectStyle/$ID/[None]" ItemTransform="1 0 0 1 396 -2378.3999999999996">
			<Properties>
				<PathGeometry>
					<GeometryPathType PathOpen="false">
						<PathPointArray>
							<PathPointType Anchor="-360 2565" LeftDirection="-360 2565" RightDirection="-360 2565" />
							<PathPointType Anchor="-360 2615.4" LeftDirection="-360 2615.4" RightDirection="-360 2615.4" />
							<PathPointType Anchor="360 2615.4" LeftDirection="360 2615.4" RightDirection="360 2615.4" />
							<PathPointType Anchor="360 2565" LeftDirection="360 2565" RightDirection="360 2565" />
						</PathPointArray>
					</GeometryPathType>
				</PathGeometry>
			</Properties>
			<TextFramePreference FootnotesEnableOverrides="false" FootnotesSpanAcrossColumns="false" FootnotesMinimumSpacing="12" FootnotesSpaceBetween="6" TextColumnCount="1" TextColumnFixedWidth="720" TextColumnMaxWidth="0">
				<Properties>
					<InsetSpacing type="list">
						<ListItem type="unit">0</ListItem>
						<ListItem type="unit">0</ListItem>
						<ListItem type="unit">0</ListItem>
						<ListItem type="unit">0</ListItem>
					</InsetSpacing>
				</Properties>
			</TextFramePreference>
			<TextFrameFootnoteOptionsObject EnableOverrides="false" SpanFootnotesAcross="false" MinimumSpacingOption="12" SpaceBetweenFootnotes="6" />
			<TextWrapPreference Inverse="false" ApplyToMasterPageOnly="false" TextWrapSide="BothSides" TextWrapMode="None">
				<Properties>
					<TextWrapOffset Top="0" Left="0" Bottom="0" Right="0" />
				</Properties>
			</TextWrapPreference>
			<ObjectExportOption AltTextSourceType="SourceXMLStructure" ActualTextSourceType="SourceXMLStructure" CustomAltText="$ID/" CustomActualText="$ID/" ApplyTagType="TagFromStructure" ImageConversionType="JPEG" ImageExportResolution="Ppi300" GIFOptionsPalette="AdaptivePalette" GIFOptionsInterlaced="true" JPEGOptionsQuality="High" JPEGOptionsFormat="BaselineEncoding" ImageAlignment="AlignLeft" ImageSpaceBefore="0" ImageSpaceAfter="0" UseImagePageBreak="false" ImagePageBreak="PageBreakBefore" CustomImageAlignment="false" SpaceUnit="CssPixel" CustomLayout="false" CustomLayoutType="AlignmentAndSpacing" EpubType="$ID/" SizeType="DefaultSize" CustomSize="$ID/" PreserveAppearanceFromLayout="PreserveAppearanceDefault">
				<Properties>
					<AltMetadataProperty NamespacePrefix="$ID/" PropertyPath="$ID/" />
					<ActualMetadataProperty NamespacePrefix="$ID/" PropertyPath="$ID/" />
				</Properties>
			</ObjectExportOption>
		</TextFrame>
	</Spread>
</idPkg:Spread>
